{
  "parent": "minecraft:recipes/root",
  "rewards": {
    "recipes": [
      "architects_palette:dark_oak_board_wall"
    ]
  },
  "criteria": {
    "has_dark_oak_boards": {
      "trigger": "minecraft:inventory_changed",
      "conditions": {
        "items": [
          {
            "items": [
              "architects_palette:dark_oak_boards"
            ]
          }
        ]
      }
    },
    "has_the_recipe": {
      "trigger": "minecraft:recipe_unlocked",
      "conditions": {
        "recipe": "architects_palette:dark_oak_board_wall"
      }
    }
  },
  "requirements": [
    [
      "has_dark_oak_boards",
      "has_the_recipe"
    ]
  ]
}